{
  "publication": {
    "reference_number": "3587",
    "publication_type": "article",
    "title": "PAQUAY J. De oudste oorkonden van Beeringen",
    "auteurs": [],
    "place_of_publication": null,
    "publisher": null,
    "publication_dates": "1928",
    "volume": null,
    "tome": null,
    "pages": null,
    "series": null,
    "journal_title": "Bulletin de la Société scientifique et littéraire du Limbourg",
    "journal_volume": "42",
    "journal_issue": null,
    "container_title": null,
    "container_editors": []
  },
  "content": {
    "main_institution": null,
    "mentioned_place": null,
    "region": null,
    "country": null,
    "institution_type": null,
    "religious_order": null,
    "temporal_coverage": null,
    "document_type": "charter"
  },
  "remarks": null
}